aliyuncli/__init__.py
aliyuncli/aliyunCliConfiugre.py
aliyuncli/aliyunCliHelp.py
aliyuncli/aliyunCliMain.py
aliyuncli/aliyunCliParser.py
aliyuncli/aliyunCliUpgrade.py
aliyuncli/aliyunCompleter.py
aliyuncli/aliyunExtensionCliHandler.py
aliyuncli/aliyunOpenApiData.py
aliyuncli/aliyunSdkConfigure.py
aliyuncli/aliyun_completer.py
aliyuncli/aliyuncli.py
aliyuncli/cliError.py
aliyuncli/commandConfigure.py
aliyuncli/configure.py
aliyuncli/handleEndPoint.py
aliyuncli/paramOptimize.py
aliyuncli/response.py
aliyuncli/six.py
aliyuncli/table.py
aliyuncli/text.py
aliyuncli/advance/__init__.py
aliyuncli/advance/ecsExportHandler.py
aliyuncli/advance/ecsImportHandler.py
aliyuncli/advance/rdsExportHandler.py
aliyuncli/advance/rdsImportHandler.py
aliyuncli/advance/userConfigHandler.py
aliyuncli/advance/userProfileHandler.py
aliyuncli/oasadp/__init__.py
aliyuncli/oasadp/oasHandler.py
aliyuncli-2.1.9.data/scripts/aliyun_zsh_complete.sh
aliyuncli-2.1.9.dist-info/DESCRIPTION.rst
aliyuncli-2.1.9.dist-info/METADATA
aliyuncli-2.1.9.dist-info/RECORD
aliyuncli-2.1.9.dist-info/WHEEL
aliyuncli-2.1.9.dist-info/entry_points.txt
aliyuncli-2.1.9.dist-info/metadata.json
aliyuncli-2.1.9.dist-info/top_level.txt
