Metadata-Version: 2.0
Name: aliyuncli
Version: 2.1.9
Summary: Universal Command Line Environment for aliyun
Home-page: http://docs.aliyun.com/?spm=5176.1829009.1002.1.LxlLfS#/pub/aliyun-command-line-interface
Author: aliyun-developers-efficiency
Author-email: aliyun-developers-efficiency@list.alibaba-inc.com
License: UNKNOWN
Platform: unix
Platform: linux
Platform: osx
Platform: win64
Requires-Dist: colorama (<=0.3.3,>=0.2.5)
Requires-Dist: jmespath (>=0.7.0,<=0.7.1)
